langgraph_checkpoint_amazon_dynamodb-0.1.2.dist-info/licenses/LICENSE
langgraph_checkpoint_dynamodb/__init__.py
langgraph_checkpoint_dynamodb/config.py
langgraph_checkpoint_dynamodb/constants.py
langgraph_checkpoint_dynamodb/errors.py
langgraph_checkpoint_dynamodb/saver.py
langgraph_checkpoint_dynamodb/utils.py
langgraph_checkpoint_dynamodb/infra/__init__.py
langgraph_checkpoint_dynamodb/infra/checkpoint_stack.py
langgraph_checkpoint_dynamodb/tests/__init__.py
langgraph_checkpoint_dynamodb/tests/unit/__init__.py
langgraph_checkpoint_dynamodb/tests/unit/test_infra_stack.py
langgraph_checkpoint_dynamodb/tests/unit/test_saver.py
langgraph_checkpoint_amazon_dynamodb-0.1.2.dist-info/METADATA
langgraph_checkpoint_amazon_dynamodb-0.1.2.dist-info/WHEEL
langgraph_checkpoint_amazon_dynamodb-0.1.2.dist-info/top_level.txt
langgraph_checkpoint_amazon_dynamodb-0.1.2.dist-info/RECORD
