Metadata-Version: 2.4
Name: langgraph-checkpoint-amazon-dynamodb
Version: 0.1.2
Summary: Library with a single-table DynamoDB implementation of LangGraph checkpoint saver.
Author-email: Aaron Su <supaaron@amazon.com>
Project-URL: Homepage, https://github.com/aaronsu11/langgraph-checkpoint-dynamodb
Project-URL: Bug Tracker, https://github.com/aaronsu11/langgraph-checkpoint-dynamodb/issues
Classifier: Programming Language :: Python :: 3
Classifier: License :: OSI Approved :: MIT License
Classifier: Operating System :: OS Independent
Requires-Python: <4.0.0,>=3.9.0
License-File: LICENSE
Requires-Dist: langgraph>=0.2.0
Requires-Dist: aioboto3>=13.0.0
Provides-Extra: infra
Requires-Dist: aws-cdk-lib>=2.174.0; extra == "infra"
Requires-Dist: constructs<11.0.0,>=10.0.0; extra == "infra"
Dynamic: license-file
